protein_bert-1.0.1.data/scripts/create_uniref_db
protein_bert-1.0.1.data/scripts/create_uniref_h5_dataset
protein_bert-1.0.1.data/scripts/pretrain_proteinbert
protein_bert-1.0.1.data/scripts/set_h5_testset
proteinbert/__init__.py
proteinbert/conv_and_global_attention_model.py
proteinbert/existing_model_loading.py
proteinbert/finetuning.py
proteinbert/model_generation.py
proteinbert/pretraining.py
proteinbert/tokenization.py
proteinbert/uniref_dataset.py
proteinbert/shared_utils/__init__.py
proteinbert/shared_utils/reference_genome.py
proteinbert/shared_utils/util.py
protein_bert-1.0.1.dist-info/METADATA
protein_bert-1.0.1.dist-info/WHEEL
protein_bert-1.0.1.dist-info/top_level.txt
protein_bert-1.0.1.dist-info/RECORD
